[{"link":"https://www.youtube.com/watch?v=zxX2YkezQnY&t=1072"},{"link":"https://www.youtube.com/watch?v=zxX2YkezQnY&t=1073"},{"link":"https://www.youtube.com/watch?v=zxX2YkezQnY&t=1074"},{"link":"https://www.youtube.com/watch?v=zxX2YkezQnY&t=1075"},{"link":"https://www.youtube.com/watch?v=zxX2YkezQnY&t=1076"},{"link":"https://www.youtube.com/watch?v=zxX2YkezQnY&t=1077"},{"link":"https://www.youtube.com/watch?v=zxX2YkezQnY&t=1078"},{"link":"https://www.youtube.com/watch?v=zxX2YkezQnY&t=1079"},{"link":"https://www.youtube.com/watch?v=zxX2YkezQnY&t=1080"},{"link":"https://www.youtube.com/watch?v=zxX2YkezQnY&t=1081"},{"link":"https://www.youtube.com/watch?v=zxX2YkezQnY&t=1082"},{"link":"https://www.youtube.com/watch?v=zxX2YkezQnY&t=1083"},{"link":"https://www.youtube.com/watch?v=zxX2YkezQnY&t=1084"},{"link":"https://www.youtube.com/watch?v=zxX2YkezQnY&t=1085"},{"link":"https://www.youtube.com/watch?v=zxX2YkezQnY&t=1086"},{"link":"https://www.youtube.com/watch?v=zxX2YkezQnY&t=1087"},{"link":"https://www.youtube.com/watch?v=zxX2YkezQnY&t=1088"},{"link":"https://www.youtube.com/watch?v=zxX2YkezQnY&t=1089"},{"link":"https://www.youtube.com/watch?v=zxX2YkezQnY&t=1090"},{"link":"https://www.youtube.com/watch?v=zxX2YkezQnY&t=1091"},{"link":"https://www.youtube.com/watch?v=zxX2YkezQnY&t=1092"},{"link":"https://www.youtube.com/watch?v=zxX2YkezQnY&t=1093"},{"link":"https://www.youtube.com/watch?v=zxX2YkezQnY&t=1094"},{"link":"https://www.youtube.com/watch?v=zxX2YkezQnY&t=1095"},{"link":"https://www.youtube.com/watch?v=zxX2YkezQnY&t=1096"},{"link":"https://www.youtube.com/watch?v=zxX2YkezQnY&t=1097"},{"link":"https://www.youtube.com/watch?v=zxX2YkezQnY&t=1098"},{"link":"https://www.youtube.com/watch?v=zxX2YkezQnY&t=1099"}]