[{"link":"https://www.youtube.com/watch?v=zxX2YkezQnY&t=1161"},{"link":"https://www.youtube.com/watch?v=zxX2YkezQnY&t=1168"},{"link":"https://www.youtube.com/watch?v=zxX2YkezQnY&t=1169"},{"link":"https://www.youtube.com/watch?v=zxX2YkezQnY&t=1170"},{"link":"https://www.youtube.com/watch?v=zxX2YkezQnY&t=1171"},{"link":"https://www.youtube.com/watch?v=zxX2YkezQnY&t=1175"},{"link":"https://www.youtube.com/watch?v=zxX2YkezQnY&t=1179"},{"link":"https://www.youtube.com/watch?v=zxX2YkezQnY&t=1180"},{"link":"https://www.youtube.com/watch?v=zxX2YkezQnY&t=1183"}]