[
  {
    "link": "https://www.youtube.com/watch?v=q-D_2hpqnds&t=371"
  },
  {
    "link": "https://www.youtube.com/watch?v=q-D_2hpqnds&t=372"
  },
  {
    "link": "https://www.youtube.com/watch?v=q-D_2hpqnds&t=373"
  },
  {
    "link": "https://www.youtube.com/watch?v=q-D_2hpqnds&t=374"
  },
  {
    "link": "https://www.youtube.com/watch?v=q-D_2hpqnds&t=375"
  },
  {
    "link": "https://www.youtube.com/watch?v=q-D_2hpqnds&t=376"
  },
  {
    "link": "https://www.youtube.com/watch?v=q-D_2hpqnds&t=377"
  },
  {
    "link": "https://www.youtube.com/watch?v=q-D_2hpqnds&t=378"
  },
  {
    "link": "https://www.youtube.com/watch?v=q-D_2hpqnds&t=379"
  },
  {
    "link": "https://www.youtube.com/watch?v=q-D_2hpqnds&t=380"
  },
  {
    "link": "https://www.youtube.com/watch?v=q-D_2hpqnds&t=381"
  },
  {
    "link": "https://www.youtube.com/watch?v=q-D_2hpqnds&t=382"
  },
  {
    "link": "https://www.youtube.com/watch?v=q-D_2hpqnds&t=383"
  },
  {
    "link": "https://www.youtube.com/watch?v=q-D_2hpqnds&t=384"
  },
  {
    "link": "https://www.youtube.com/watch?v=q-D_2hpqnds&t=385"
  }
]