[
  {
    "link": "https://www.youtube.com/watch?v=YY2SiQkvbAE&t=1041"
  },
  {
    "link": "https://www.youtube.com/watch?v=YY2SiQkvbAE&t=1042"
  },
  {
    "link": "https://www.youtube.com/watch?v=YY2SiQkvbAE&t=1043"
  },
  {
    "link": "https://www.youtube.com/watch?v=YY2SiQkvbAE&t=1044"
  },
  {
    "link": "https://www.youtube.com/watch?v=YY2SiQkvbAE&t=1045"
  },
  {
    "link": "https://www.youtube.com/watch?v=YY2SiQkvbAE&t=1046"
  },
  {
    "link": "https://www.youtube.com/watch?v=YY2SiQkvbAE&t=1047"
  },
  {
    "link": "https://www.youtube.com/watch?v=YY2SiQkvbAE&t=1048"
  },
  {
    "link": "https://www.youtube.com/watch?v=YY2SiQkvbAE&t=1049"
  },
  {
    "link": "https://www.youtube.com/watch?v=YY2SiQkvbAE&t=1050"
  },
  {
    "link": "https://www.youtube.com/watch?v=YY2SiQkvbAE&t=1051"
  },
  {
    "link": "https://www.youtube.com/watch?v=YY2SiQkvbAE&t=1052"
  },
  {
    "link": "https://www.youtube.com/watch?v=YY2SiQkvbAE&t=1053"
  },
  {
    "link": "https://www.youtube.com/watch?v=YY2SiQkvbAE&t=1054"
  },
  {
    "link": "https://www.youtube.com/watch?v=YY2SiQkvbAE&t=1055"
  },
  {
    "link": "https://www.youtube.com/watch?v=YY2SiQkvbAE&t=1056"
  }
]