[{"link":"https://www.youtube.com/watch?v=w7a2wGaez1g&t=129"},{"link":"https://www.youtube.com/watch?v=w7a2wGaez1g&t=130"},{"link":"https://www.youtube.com/watch?v=w7a2wGaez1g&t=132"},{"link":"https://www.youtube.com/watch?v=w7a2wGaez1g&t=133"},{"link":"https://www.youtube.com/watch?v=w7a2wGaez1g&t=134"},{"link":"https://www.youtube.com/watch?v=w7a2wGaez1g&t=135"},{"link":"https://www.youtube.com/watch?v=w7a2wGaez1g&t=136"},{"link":"https://www.youtube.com/watch?v=w7a2wGaez1g&t=137"},{"link":"https://www.youtube.com/watch?v=w7a2wGaez1g&t=138"},{"link":"https://www.youtube.com/watch?v=w7a2wGaez1g&t=139"},{"link":"https://www.youtube.com/watch?v=w7a2wGaez1g&t=140"},{"link":"https://www.youtube.com/watch?v=w7a2wGaez1g&t=141"},{"link":"https://www.youtube.com/watch?v=w7a2wGaez1g&t=142"},{"link":"https://www.youtube.com/watch?v=w7a2wGaez1g&t=143"},{"link":"https://www.youtube.com/watch?v=w7a2wGaez1g&t=144"},{"link":"https://www.youtube.com/watch?v=w7a2wGaez1g&t=145"}]