[
  {
    "link": "https://www.youtube.com/watch?v=oMQwnMR6OVk&t=186"
  },
  {
    "link": "https://www.youtube.com/watch?v=oMQwnMR6OVk&t=187"
  },
  {
    "link": "https://www.youtube.com/watch?v=oMQwnMR6OVk&t=188"
  },
  {
    "link": "https://www.youtube.com/watch?v=oMQwnMR6OVk&t=189"
  },
  {
    "link": "https://www.youtube.com/watch?v=oMQwnMR6OVk&t=193"
  },
  {
    "link": "https://www.youtube.com/watch?v=oMQwnMR6OVk&t=194"
  },
  {
    "link": "https://www.youtube.com/watch?v=oMQwnMR6OVk&t=196"
  },
  {
    "link": "https://www.youtube.com/watch?v=oMQwnMR6OVk&t=197"
  },
  {
    "link": "https://www.youtube.com/watch?v=oMQwnMR6OVk&t=198"
  },
  {
    "link": "https://www.youtube.com/watch?v=oMQwnMR6OVk&t=201"
  },
  {
    "link": "https://www.youtube.com/watch?v=oMQwnMR6OVk&t=202"
  },
  {
    "link": "https://www.youtube.com/watch?v=oMQwnMR6OVk&t=203"
  },
  {
    "link": "https://www.youtube.com/watch?v=oMQwnMR6OVk&t=206"
  },
  {
    "link": "https://www.youtube.com/watch?v=oMQwnMR6OVk&t=207"
  },
  {
    "link": "https://www.youtube.com/watch?v=oMQwnMR6OVk&t=208"
  },
  {
    "link": "https://www.youtube.com/watch?v=oMQwnMR6OVk&t=209"
  },
  {
    "link": "https://www.youtube.com/watch?v=oMQwnMR6OVk&t=211"
  }
]