[{"link":"https://www.youtube.com/watch?v=ebfzL_GwiIE&t=114"},{"link":"https://www.youtube.com/watch?v=ebfzL_GwiIE&t=116"},{"link":"https://www.youtube.com/watch?v=ebfzL_GwiIE&t=118"},{"link":"https://www.youtube.com/watch?v=ebfzL_GwiIE&t=119"},{"link":"https://www.youtube.com/watch?v=ebfzL_GwiIE&t=120"},{"link":"https://www.youtube.com/watch?v=ebfzL_GwiIE&t=121"},{"link":"https://www.youtube.com/watch?v=ebfzL_GwiIE&t=122"},{"link":"https://www.youtube.com/watch?v=ebfzL_GwiIE&t=124"},{"link":"https://www.youtube.com/watch?v=ebfzL_GwiIE&t=125"},{"link":"https://www.youtube.com/watch?v=ebfzL_GwiIE&t=127"},{"link":"https://www.youtube.com/watch?v=ebfzL_GwiIE&t=128"},{"link":"https://www.youtube.com/watch?v=ebfzL_GwiIE&t=130"},{"link":"https://www.youtube.com/watch?v=ebfzL_GwiIE&t=131"},{"link":"https://www.youtube.com/watch?v=ebfzL_GwiIE&t=132"},{"link":"https://www.youtube.com/watch?v=ebfzL_GwiIE&t=135"}]