[{"link":"https://www.youtube.com/watch?v=esbm4nL5G-A&t=484"},{"link":"https://www.youtube.com/watch?v=esbm4nL5G-A&t=485"},{"link":"https://www.youtube.com/watch?v=esbm4nL5G-A&t=486"},{"link":"https://www.youtube.com/watch?v=esbm4nL5G-A&t=487"},{"link":"https://www.youtube.com/watch?v=esbm4nL5G-A&t=493"},{"link":"https://www.youtube.com/watch?v=esbm4nL5G-A&t=494"},{"link":"https://www.youtube.com/watch?v=esbm4nL5G-A&t=496"},{"link":"https://www.youtube.com/watch?v=esbm4nL5G-A&t=497"},{"link":"https://www.youtube.com/watch?v=esbm4nL5G-A&t=498"},{"link":"https://www.youtube.com/watch?v=esbm4nL5G-A&t=499"},{"link":"https://www.youtube.com/watch?v=esbm4nL5G-A&t=500"},{"link":"https://www.youtube.com/watch?v=esbm4nL5G-A&t=501"},{"link":"https://www.youtube.com/watch?v=esbm4nL5G-A&t=502"},{"link":"https://www.youtube.com/watch?v=esbm4nL5G-A&t=503"},{"link":"https://www.youtube.com/watch?v=esbm4nL5G-A&t=505"},{"link":"https://www.youtube.com/watch?v=esbm4nL5G-A&t=506"},{"link":"https://www.youtube.com/watch?v=esbm4nL5G-A&t=507"},{"link":"https://www.youtube.com/watch?v=esbm4nL5G-A&t=508"},{"link":"https://www.youtube.com/watch?v=esbm4nL5G-A&t=509"},{"link":"https://www.youtube.com/watch?v=esbm4nL5G-A&t=510"},{"link":"https://www.youtube.com/watch?v=esbm4nL5G-A&t=511"},{"link":"https://www.youtube.com/watch?v=esbm4nL5G-A&t=512"},{"link":"https://www.youtube.com/watch?v=esbm4nL5G-A&t=513"},{"link":"https://www.youtube.com/watch?v=esbm4nL5G-A&t=514"},{"link":"https://www.youtube.com/watch?v=esbm4nL5G-A&t=515"},{"link":"https://www.youtube.com/watch?v=esbm4nL5G-A&t=516"},{"link":"https://www.youtube.com/watch?v=esbm4nL5G-A&t=517"},{"link":"https://www.youtube.com/watch?v=esbm4nL5G-A&t=518"},{"link":"https://www.youtube.com/watch?v=nF6itO851ik&t=100"},{"link":"https://www.youtube.com/watch?v=nF6itO851ik&t=101"},{"link":"https://www.youtube.com/watch?v=nF6itO851ik&t=102"},{"link":"https://www.youtube.com/watch?v=nF6itO851ik&t=94"},{"link":"https://www.youtube.com/watch?v=nF6itO851ik&t=95"},{"link":"https://www.youtube.com/watch?v=nF6itO851ik&t=96"},{"link":"https://www.youtube.com/watch?v=nF6itO851ik&t=97"},{"link":"https://www.youtube.com/watch?v=nF6itO851ik&t=98"},{"link":"https://www.youtube.com/watch?v=nF6itO851ik&t=99"}]