[{"link":"https://www.youtube.com/watch?v=0ITi9Jc0J-o&t=141"},{"link":"https://www.youtube.com/watch?v=0ITi9Jc0J-o&t=142"},{"link":"https://www.youtube.com/watch?v=0ITi9Jc0J-o&t=143"},{"link":"https://www.youtube.com/watch?v=0ITi9Jc0J-o&t=144"},{"link":"https://www.youtube.com/watch?v=0ITi9Jc0J-o&t=145"},{"link":"https://www.youtube.com/watch?v=0ITi9Jc0J-o&t=146"},{"link":"https://www.youtube.com/watch?v=hLFSufXxtuI&t=100"},{"link":"https://www.youtube.com/watch?v=hLFSufXxtuI&t=102"},{"link":"https://www.youtube.com/watch?v=hLFSufXxtuI&t=103"},{"link":"https://www.youtube.com/watch?v=hLFSufXxtuI&t=104"},{"link":"https://www.youtube.com/watch?v=hLFSufXxtuI&t=105"},{"link":"https://www.youtube.com/watch?v=hLFSufXxtuI&t=106"},{"link":"https://www.youtube.com/watch?v=hLFSufXxtuI&t=107"},{"link":"https://www.youtube.com/watch?v=hLFSufXxtuI&t=108"},{"link":"https://www.youtube.com/watch?v=hLFSufXxtuI&t=323"},{"link":"https://www.youtube.com/watch?v=hLFSufXxtuI&t=324"},{"link":"https://www.youtube.com/watch?v=hLFSufXxtuI&t=325"},{"link":"https://www.youtube.com/watch?v=hLFSufXxtuI&t=326"},{"link":"https://www.youtube.com/watch?v=hLFSufXxtuI&t=98"},{"link":"https://www.youtube.com/watch?v=hLFSufXxtuI&t=99"},{"link":"https://www.youtube.com/watch?v=MHTa3aDczCk&t=705"},{"link":"https://www.youtube.com/watch?v=oNufRD0fYzE&t=177"},{"link":"https://www.youtube.com/watch?v=oNufRD0fYzE&t=178"},{"link":"https://www.youtube.com/watch?v=oNufRD0fYzE&t=179"},{"link":"https://www.youtube.com/watch?v=oNufRD0fYzE&t=180"},{"link":"https://www.youtube.com/watch?v=oNufRD0fYzE&t=182"},{"link":"https://www.youtube.com/watch?v=oNufRD0fYzE&t=185"},{"link":"https://www.youtube.com/watch?v=oNufRD0fYzE&t=187"},{"link":"https://www.youtube.com/watch?v=oNufRD0fYzE&t=190"},{"link":"https://www.youtube.com/watch?v=oNufRD0fYzE&t=191"},{"link":"https://www.youtube.com/watch?v=oNufRD0fYzE&t=192"},{"link":"https://www.youtube.com/watch?v=oNufRD0fYzE&t=193"},{"link":"https://www.youtube.com/watch?v=oNufRD0fYzE&t=196"},{"link":"https://www.youtube.com/watch?v=oNufRD0fYzE&t=251"},{"link":"https://www.youtube.com/watch?v=ZmF64w13ZU8&t=1179"},{"link":"https://www.youtube.com/watch?v=ZmF64w13ZU8&t=73"},{"link":"https://www.youtube.com/watch?v=ZmF64w13ZU8&t=74"}]