[
  {
    "link": "https://www.youtube.com/watch?v=ZmF64w13ZU8&t=353"
  },
  {
    "link": "https://www.youtube.com/watch?v=ZmF64w13ZU8&t=355"
  },
  {
    "link": "https://www.youtube.com/watch?v=ZmF64w13ZU8&t=356"
  },
  {
    "link": "https://www.youtube.com/watch?v=ZmF64w13ZU8&t=423"
  },
  {
    "link": "https://www.youtube.com/watch?v=ZmF64w13ZU8&t=424"
  },
  {
    "link": "https://www.youtube.com/watch?v=ZmF64w13ZU8&t=426"
  },
  {
    "link": "https://www.youtube.com/watch?v=ZmF64w13ZU8&t=427"
  }
]