[{"link":"https://www.youtube.com/watch?v=7IRZDlqNbH0&t=105"},{"link":"https://www.youtube.com/watch?v=7IRZDlqNbH0&t=107"},{"link":"https://www.youtube.com/watch?v=7IRZDlqNbH0&t=108"},{"link":"https://www.youtube.com/watch?v=7IRZDlqNbH0&t=109"},{"link":"https://www.youtube.com/watch?v=7IRZDlqNbH0&t=110"},{"link":"https://www.youtube.com/watch?v=7IRZDlqNbH0&t=111"},{"link":"https://www.youtube.com/watch?v=7IRZDlqNbH0&t=113"},{"link":"https://www.youtube.com/watch?v=7IRZDlqNbH0&t=114"},{"link":"https://www.youtube.com/watch?v=7IRZDlqNbH0&t=115"},{"link":"https://www.youtube.com/watch?v=7IRZDlqNbH0&t=116"},{"link":"https://www.youtube.com/watch?v=7IRZDlqNbH0&t=117"},{"link":"https://www.youtube.com/watch?v=7IRZDlqNbH0&t=120"},{"link":"https://www.youtube.com/watch?v=7IRZDlqNbH0&t=121"},{"link":"https://www.youtube.com/watch?v=7IRZDlqNbH0&t=122"},{"link":"https://www.youtube.com/watch?v=7IRZDlqNbH0&t=123"},{"link":"https://www.youtube.com/watch?v=7IRZDlqNbH0&t=124"},{"link":"https://www.youtube.com/watch?v=7IRZDlqNbH0&t=127"},{"link":"https://www.youtube.com/watch?v=7IRZDlqNbH0&t=129"},{"link":"https://www.youtube.com/watch?v=vTmK65znX2o&t=249"},{"link":"https://www.youtube.com/watch?v=vTmK65znX2o&t=250"},{"link":"https://www.youtube.com/watch?v=vTmK65znX2o&t=251"}]