[{"link":"https://www.youtube.com/watch?v=6187BUdcK34&t=654"},{"link":"https://www.youtube.com/watch?v=6187BUdcK34&t=655"},{"link":"https://www.youtube.com/watch?v=6187BUdcK34&t=656"},{"link":"https://www.youtube.com/watch?v=6187BUdcK34&t=657"},{"link":"https://www.youtube.com/watch?v=6187BUdcK34&t=659"},{"link":"https://www.youtube.com/watch?v=6187BUdcK34&t=660"},{"link":"https://www.youtube.com/watch?v=6187BUdcK34&t=673"},{"link":"https://www.youtube.com/watch?v=6187BUdcK34&t=674"},{"link":"https://www.youtube.com/watch?v=6187BUdcK34&t=675"},{"link":"https://www.youtube.com/watch?v=6187BUdcK34&t=676"},{"link":"https://www.youtube.com/watch?v=6187BUdcK34&t=678"},{"link":"https://www.youtube.com/watch?v=6187BUdcK34&t=679"},{"link":"https://www.youtube.com/watch?v=6187BUdcK34&t=680"},{"link":"https://www.youtube.com/watch?v=6187BUdcK34&t=682"},{"link":"https://www.youtube.com/watch?v=6187BUdcK34&t=683"},{"link":"https://www.youtube.com/watch?v=6187BUdcK34&t=684"},{"link":"https://www.youtube.com/watch?v=6187BUdcK34&t=685"}]