[
  {
    "link": "https://www.youtube.com/watch?v=XETFf3k6xUU&t=695"
  },
  {
    "link": "https://www.youtube.com/watch?v=XETFf3k6xUU&t=696"
  },
  {
    "link": "https://www.youtube.com/watch?v=XETFf3k6xUU&t=707"
  },
  {
    "link": "https://www.youtube.com/watch?v=XETFf3k6xUU&t=709"
  },
  {
    "link": "https://www.youtube.com/watch?v=XETFf3k6xUU&t=711"
  },
  {
    "link": "https://www.youtube.com/watch?v=XETFf3k6xUU&t=718"
  },
  {
    "link": "https://www.youtube.com/watch?v=XETFf3k6xUU&t=728"
  }
]