[{"link":"https://www.youtube.com/watch?v=ECMMct_jnEM&t=1502"},{"link":"https://www.youtube.com/watch?v=ECMMct_jnEM&t=1503"},{"link":"https://www.youtube.com/watch?v=ECMMct_jnEM&t=1504"},{"link":"https://www.youtube.com/watch?v=ECMMct_jnEM&t=1506"},{"link":"https://www.youtube.com/watch?v=ECMMct_jnEM&t=1507"},{"link":"https://www.youtube.com/watch?v=ECMMct_jnEM&t=1508"},{"link":"https://www.youtube.com/watch?v=ECMMct_jnEM&t=1509"},{"link":"https://www.youtube.com/watch?v=ECMMct_jnEM&t=1510"},{"link":"https://www.youtube.com/watch?v=ECMMct_jnEM&t=1512"},{"link":"https://www.youtube.com/watch?v=ECMMct_jnEM&t=1514"},{"link":"https://www.youtube.com/watch?v=ECMMct_jnEM&t=1515"}]