[
  {
    "link": "https://www.youtube.com/watch?v=7IRZDlqNbH0&t=1596"
  },
  {
    "link": "https://www.youtube.com/watch?v=7IRZDlqNbH0&t=1597"
  },
  {
    "link": "https://www.youtube.com/watch?v=7IRZDlqNbH0&t=1599"
  },
  {
    "link": "https://www.youtube.com/watch?v=7IRZDlqNbH0&t=1600"
  },
  {
    "link": "https://www.youtube.com/watch?v=7IRZDlqNbH0&t=1602"
  },
  {
    "link": "https://www.youtube.com/watch?v=7IRZDlqNbH0&t=1603"
  },
  {
    "link": "https://www.youtube.com/watch?v=7IRZDlqNbH0&t=1604"
  },
  {
    "link": "https://www.youtube.com/watch?v=7IRZDlqNbH0&t=1613"
  },
  {
    "link": "https://www.youtube.com/watch?v=7IRZDlqNbH0&t=1615"
  },
  {
    "link": "https://www.youtube.com/watch?v=7IRZDlqNbH0&t=1616"
  },
  {
    "link": "https://www.youtube.com/watch?v=7IRZDlqNbH0&t=1617"
  },
  {
    "link": "https://www.youtube.com/watch?v=7IRZDlqNbH0&t=1618"
  },
  {
    "link": "https://www.youtube.com/watch?v=7IRZDlqNbH0&t=1619"
  },
  {
    "link": "https://www.youtube.com/watch?v=7IRZDlqNbH0&t=1623"
  },
  {
    "link": "https://www.youtube.com/watch?v=7IRZDlqNbH0&t=1624"
  },
  {
    "link": "https://www.youtube.com/watch?v=7IRZDlqNbH0&t=1625"
  },
  {
    "link": "https://www.youtube.com/watch?v=7IRZDlqNbH0&t=1626"
  }
]