[
  {
    "link": "https://www.youtube.com/watch?v=6187BUdcK34&t=875"
  },
  {
    "link": "https://www.youtube.com/watch?v=Qb3PWiIbIJs&t=215"
  },
  {
    "link": "https://www.youtube.com/watch?v=Qb3PWiIbIJs&t=216"
  },
  {
    "link": "https://www.youtube.com/watch?v=Qb3PWiIbIJs&t=217"
  },
  {
    "link": "https://www.youtube.com/watch?v=Qb3PWiIbIJs&t=295"
  },
  {
    "link": "https://www.youtube.com/watch?v=Qb3PWiIbIJs&t=298"
  },
  {
    "link": "https://www.youtube.com/watch?v=Qb3PWiIbIJs&t=300"
  },
  {
    "link": "https://www.youtube.com/watch?v=Qb3PWiIbIJs&t=301"
  }
]