[
  {
    "link": "https://www.youtube.com/watch?v=51vnCWXXLGc&t=563"
  },
  {
    "link": "https://www.youtube.com/watch?v=51vnCWXXLGc&t=564"
  },
  {
    "link": "https://www.youtube.com/watch?v=51vnCWXXLGc&t=565"
  },
  {
    "link": "https://www.youtube.com/watch?v=51vnCWXXLGc&t=566"
  },
  {
    "link": "https://www.youtube.com/watch?v=51vnCWXXLGc&t=569"
  },
  {
    "link": "https://www.youtube.com/watch?v=51vnCWXXLGc&t=570"
  },
  {
    "link": "https://www.youtube.com/watch?v=51vnCWXXLGc&t=571"
  },
  {
    "link": "https://www.youtube.com/watch?v=51vnCWXXLGc&t=572"
  },
  {
    "link": "https://www.youtube.com/watch?v=51vnCWXXLGc&t=573"
  },
  {
    "link": "https://www.youtube.com/watch?v=51vnCWXXLGc&t=574"
  },
  {
    "link": "https://www.youtube.com/watch?v=51vnCWXXLGc&t=576"
  },
  {
    "link": "https://www.youtube.com/watch?v=51vnCWXXLGc&t=579"
  },
  {
    "link": "https://www.youtube.com/watch?v=51vnCWXXLGc&t=583"
  },
  {
    "link": "https://www.youtube.com/watch?v=51vnCWXXLGc&t=584"
  },
  {
    "link": "https://www.youtube.com/watch?v=51vnCWXXLGc&t=586"
  },
  {
    "link": "https://www.youtube.com/watch?v=51vnCWXXLGc&t=587"
  },
  {
    "link": "https://www.youtube.com/watch?v=51vnCWXXLGc&t=588"
  },
  {
    "link": "https://www.youtube.com/watch?v=51vnCWXXLGc&t=590"
  },
  {
    "link": "https://www.youtube.com/watch?v=51vnCWXXLGc&t=591"
  },
  {
    "link": "https://www.youtube.com/watch?v=51vnCWXXLGc&t=593"
  },
  {
    "link": "https://www.youtube.com/watch?v=51vnCWXXLGc&t=594"
  },
  {
    "link": "https://www.youtube.com/watch?v=51vnCWXXLGc&t=597"
  },
  {
    "link": "https://www.youtube.com/watch?v=51vnCWXXLGc&t=598"
  },
  {
    "link": "https://www.youtube.com/watch?v=51vnCWXXLGc&t=599"
  },
  {
    "link": "https://www.youtube.com/watch?v=51vnCWXXLGc&t=600"
  },
  {
    "link": "https://www.youtube.com/watch?v=51vnCWXXLGc&t=601"
  },
  {
    "link": "https://www.youtube.com/watch?v=51vnCWXXLGc&t=602"
  },
  {
    "link": "https://www.youtube.com/watch?v=51vnCWXXLGc&t=603"
  },
  {
    "link": "https://www.youtube.com/watch?v=51vnCWXXLGc&t=604"
  },
  {
    "link": "https://www.youtube.com/watch?v=51vnCWXXLGc&t=605"
  },
  {
    "link": "https://www.youtube.com/watch?v=51vnCWXXLGc&t=606"
  },
  {
    "link": "https://www.youtube.com/watch?v=51vnCWXXLGc&t=607"
  },
  {
    "link": "https://www.youtube.com/watch?v=51vnCWXXLGc&t=608"
  },
  {
    "link": "https://www.youtube.com/watch?v=51vnCWXXLGc&t=609"
  },
  {
    "link": "https://www.youtube.com/watch?v=51vnCWXXLGc&t=610"
  },
  {
    "link": "https://www.youtube.com/watch?v=51vnCWXXLGc&t=611"
  },
  {
    "link": "https://www.youtube.com/watch?v=51vnCWXXLGc&t=612"
  }
]