[
  {
    "link": "https://www.youtube.com/watch?v=i7bG2VNIW3A&t=307"
  },
  {
    "link": "https://www.youtube.com/watch?v=i7bG2VNIW3A&t=308"
  },
  {
    "link": "https://www.youtube.com/watch?v=i7bG2VNIW3A&t=309"
  },
  {
    "link": "https://www.youtube.com/watch?v=i7bG2VNIW3A&t=310"
  },
  {
    "link": "https://www.youtube.com/watch?v=i7bG2VNIW3A&t=311"
  },
  {
    "link": "https://www.youtube.com/watch?v=i7bG2VNIW3A&t=312"
  },
  {
    "link": "https://www.youtube.com/watch?v=i7bG2VNIW3A&t=313"
  },
  {
    "link": "https://www.youtube.com/watch?v=i7bG2VNIW3A&t=314"
  },
  {
    "link": "https://www.youtube.com/watch?v=i7bG2VNIW3A&t=315"
  },
  {
    "link": "https://www.youtube.com/watch?v=i7bG2VNIW3A&t=316"
  },
  {
    "link": "https://www.youtube.com/watch?v=i7bG2VNIW3A&t=317"
  },
  {
    "link": "https://www.youtube.com/watch?v=i7bG2VNIW3A&t=318"
  },
  {
    "link": "https://www.youtube.com/watch?v=i7bG2VNIW3A&t=319"
  },
  {
    "link": "https://www.youtube.com/watch?v=i7bG2VNIW3A&t=320"
  }
]