[
  {
    "link": "https://www.youtube.com/watch?v=bTCjp34DkMM&t=892"
  },
  {
    "link": "https://www.youtube.com/watch?v=bTCjp34DkMM&t=893"
  },
  {
    "link": "https://www.youtube.com/watch?v=bTCjp34DkMM&t=894"
  },
  {
    "link": "https://www.youtube.com/watch?v=bTCjp34DkMM&t=895"
  },
  {
    "link": "https://www.youtube.com/watch?v=bTCjp34DkMM&t=896"
  },
  {
    "link": "https://www.youtube.com/watch?v=bTCjp34DkMM&t=897"
  },
  {
    "link": "https://www.youtube.com/watch?v=bTCjp34DkMM&t=898"
  },
  {
    "link": "https://www.youtube.com/watch?v=bTCjp34DkMM&t=899"
  },
  {
    "link": "https://www.youtube.com/watch?v=bTCjp34DkMM&t=900"
  },
  {
    "link": "https://www.youtube.com/watch?v=bTCjp34DkMM&t=901"
  },
  {
    "link": "https://www.youtube.com/watch?v=bTCjp34DkMM&t=902"
  },
  {
    "link": "https://www.youtube.com/watch?v=bTCjp34DkMM&t=903"
  },
  {
    "link": "https://www.youtube.com/watch?v=bTCjp34DkMM&t=904"
  },
  {
    "link": "https://www.youtube.com/watch?v=bTCjp34DkMM&t=905"
  },
  {
    "link": "https://www.youtube.com/watch?v=bTCjp34DkMM&t=906"
  },
  {
    "link": "https://www.youtube.com/watch?v=bTCjp34DkMM&t=907"
  },
  {
    "link": "https://www.youtube.com/watch?v=bTCjp34DkMM&t=908"
  },
  {
    "link": "https://www.youtube.com/watch?v=bTCjp34DkMM&t=909"
  },
  {
    "link": "https://www.youtube.com/watch?v=bTCjp34DkMM&t=910"
  },
  {
    "link": "https://www.youtube.com/watch?v=bTCjp34DkMM&t=911"
  },
  {
    "link": "https://www.youtube.com/watch?v=bTCjp34DkMM&t=912"
  },
  {
    "link": "https://www.youtube.com/watch?v=bTCjp34DkMM&t=913"
  },
  {
    "link": "https://www.youtube.com/watch?v=bTCjp34DkMM&t=914"
  },
  {
    "link": "https://www.youtube.com/watch?v=bTCjp34DkMM&t=915"
  },
  {
    "link": "https://www.youtube.com/watch?v=bTCjp34DkMM&t=916"
  },
  {
    "link": "https://www.youtube.com/watch?v=bTCjp34DkMM&t=917"
  },
  {
    "link": "https://www.youtube.com/watch?v=bTCjp34DkMM&t=918"
  },
  {
    "link": "https://www.youtube.com/watch?v=bTCjp34DkMM&t=919"
  },
  {
    "link": "https://www.youtube.com/watch?v=bTCjp34DkMM&t=920"
  },
  {
    "link": "https://www.youtube.com/watch?v=bTCjp34DkMM&t=921"
  },
  {
    "link": "https://www.youtube.com/watch?v=bTCjp34DkMM&t=922"
  },
  {
    "link": "https://www.youtube.com/watch?v=bTCjp34DkMM&t=923"
  },
  {
    "link": "https://www.youtube.com/watch?v=bTCjp34DkMM&t=924"
  },
  {
    "link": "https://www.youtube.com/watch?v=bTCjp34DkMM&t=925"
  },
  {
    "link": "https://www.youtube.com/watch?v=bTCjp34DkMM&t=926"
  },
  {
    "link": "https://www.youtube.com/watch?v=bTCjp34DkMM&t=927"
  },
  {
    "link": "https://www.youtube.com/watch?v=bTCjp34DkMM&t=928"
  },
  {
    "link": "https://www.youtube.com/watch?v=bTCjp34DkMM&t=929"
  },
  {
    "link": "https://www.youtube.com/watch?v=bTCjp34DkMM&t=930"
  },
  {
    "link": "https://www.youtube.com/watch?v=bTCjp34DkMM&t=931"
  },
  {
    "link": "https://www.youtube.com/watch?v=bTCjp34DkMM&t=932"
  },
  {
    "link": "https://www.youtube.com/watch?v=bTCjp34DkMM&t=933"
  },
  {
    "link": "https://www.youtube.com/watch?v=bTCjp34DkMM&t=935"
  },
  {
    "link": "https://www.youtube.com/watch?v=bTCjp34DkMM&t=937"
  },
  {
    "link": "https://www.youtube.com/watch?v=bTCjp34DkMM&t=938"
  },
  {
    "link": "https://www.youtube.com/watch?v=bTCjp34DkMM&t=944"
  },
  {
    "link": "https://www.youtube.com/watch?v=bTCjp34DkMM&t=946"
  },
  {
    "link": "https://www.youtube.com/watch?v=bTCjp34DkMM&t=947"
  },
  {
    "link": "https://www.youtube.com/watch?v=bTCjp34DkMM&t=952"
  },
  {
    "link": "https://www.youtube.com/watch?v=bTCjp34DkMM&t=953"
  },
  {
    "link": "https://www.youtube.com/watch?v=bTCjp34DkMM&t=955"
  },
  {
    "link": "https://www.youtube.com/watch?v=bTCjp34DkMM&t=957"
  },
  {
    "link": "https://www.youtube.com/watch?v=bTCjp34DkMM&t=960"
  },
  {
    "link": "https://www.youtube.com/watch?v=bTCjp34DkMM&t=962"
  },
  {
    "link": "https://www.youtube.com/watch?v=bTCjp34DkMM&t=963"
  },
  {
    "link": "https://www.youtube.com/watch?v=bTCjp34DkMM&t=964"
  },
  {
    "link": "https://www.youtube.com/watch?v=bTCjp34DkMM&t=965"
  },
  {
    "link": "https://www.youtube.com/watch?v=bTCjp34DkMM&t=967"
  },
  {
    "link": "https://www.youtube.com/watch?v=bTCjp34DkMM&t=968"
  },
  {
    "link": "https://www.youtube.com/watch?v=bTCjp34DkMM&t=969"
  },
  {
    "link": "https://www.youtube.com/watch?v=bTCjp34DkMM&t=970"
  },
  {
    "link": "https://www.youtube.com/watch?v=bTCjp34DkMM&t=971"
  },
  {
    "link": "https://www.youtube.com/watch?v=bTCjp34DkMM&t=972"
  },
  {
    "link": "https://www.youtube.com/watch?v=bTCjp34DkMM&t=973"
  },
  {
    "link": "https://www.youtube.com/watch?v=bTCjp34DkMM&t=974"
  },
  {
    "link": "https://www.youtube.com/watch?v=bTCjp34DkMM&t=975"
  },
  {
    "link": "https://www.youtube.com/watch?v=bTCjp34DkMM&t=976"
  },
  {
    "link": "https://www.youtube.com/watch?v=bTCjp34DkMM&t=977"
  },
  {
    "link": "https://www.youtube.com/watch?v=bTCjp34DkMM&t=978"
  },
  {
    "link": "https://www.youtube.com/watch?v=bTCjp34DkMM&t=979"
  },
  {
    "link": "https://www.youtube.com/watch?v=bTCjp34DkMM&t=980"
  },
  {
    "link": "https://www.youtube.com/watch?v=bTCjp34DkMM&t=981"
  },
  {
    "link": "https://www.youtube.com/watch?v=bTCjp34DkMM&t=982"
  },
  {
    "link": "https://www.youtube.com/watch?v=bTCjp34DkMM&t=983"
  },
  {
    "link": "https://www.youtube.com/watch?v=bTCjp34DkMM&t=984"
  },
  {
    "link": "https://www.youtube.com/watch?v=bTCjp34DkMM&t=985"
  },
  {
    "link": "https://www.youtube.com/watch?v=bTCjp34DkMM&t=986"
  },
  {
    "link": "https://www.youtube.com/watch?v=bTCjp34DkMM&t=987"
  },
  {
    "link": "https://www.youtube.com/watch?v=bTCjp34DkMM&t=988"
  },
  {
    "link": "https://www.youtube.com/watch?v=bTCjp34DkMM&t=989"
  },
  {
    "link": "https://www.youtube.com/watch?v=bTCjp34DkMM&t=990"
  },
  {
    "link": "https://www.youtube.com/watch?v=bTCjp34DkMM&t=991"
  },
  {
    "link": "https://www.youtube.com/watch?v=bTCjp34DkMM&t=992"
  },
  {
    "link": "https://www.youtube.com/watch?v=bTCjp34DkMM&t=993"
  },
  {
    "link": "https://www.youtube.com/watch?v=bTCjp34DkMM&t=994"
  },
  {
    "link": "https://www.youtube.com/watch?v=bTCjp34DkMM&t=995"
  },
  {
    "link": "https://www.youtube.com/watch?v=bTCjp34DkMM&t=996"
  },
  {
    "link": "https://www.youtube.com/watch?v=bTCjp34DkMM&t=997"
  },
  {
    "link": "https://www.youtube.com/watch?v=bTCjp34DkMM&t=998"
  }
]