[
  {
    "link": "https://www.youtube.com/watch?v=qP7JsrhVg6w&t=1340"
  },
  {
    "link": "https://www.youtube.com/watch?v=qP7JsrhVg6w&t=1341"
  },
  {
    "link": "https://www.youtube.com/watch?v=qP7JsrhVg6w&t=1342"
  },
  {
    "link": "https://www.youtube.com/watch?v=qP7JsrhVg6w&t=1343"
  },
  {
    "link": "https://www.youtube.com/watch?v=qP7JsrhVg6w&t=1344"
  },
  {
    "link": "https://www.youtube.com/watch?v=qP7JsrhVg6w&t=1347"
  },
  {
    "link": "https://www.youtube.com/watch?v=qP7JsrhVg6w&t=1349"
  },
  {
    "link": "https://www.youtube.com/watch?v=qP7JsrhVg6w&t=1350"
  },
  {
    "link": "https://www.youtube.com/watch?v=qP7JsrhVg6w&t=1351"
  },
  {
    "link": "https://www.youtube.com/watch?v=qP7JsrhVg6w&t=1352"
  },
  {
    "link": "https://www.youtube.com/watch?v=qP7JsrhVg6w&t=1353"
  },
  {
    "link": "https://www.youtube.com/watch?v=qP7JsrhVg6w&t=1354"
  }
]