[
  {
    "link": "https://www.youtube.com/watch?v=bA22QfIhn9Y&t=302"
  },
  {
    "link": "https://www.youtube.com/watch?v=bA22QfIhn9Y&t=303"
  },
  {
    "link": "https://www.youtube.com/watch?v=bA22QfIhn9Y&t=304"
  },
  {
    "link": "https://www.youtube.com/watch?v=bA22QfIhn9Y&t=305"
  },
  {
    "link": "https://www.youtube.com/watch?v=bA22QfIhn9Y&t=306"
  },
  {
    "link": "https://www.youtube.com/watch?v=bA22QfIhn9Y&t=307"
  },
  {
    "link": "https://www.youtube.com/watch?v=bA22QfIhn9Y&t=308"
  },
  {
    "link": "https://www.youtube.com/watch?v=bA22QfIhn9Y&t=309"
  },
  {
    "link": "https://www.youtube.com/watch?v=bA22QfIhn9Y&t=310"
  },
  {
    "link": "https://www.youtube.com/watch?v=bA22QfIhn9Y&t=311"
  },
  {
    "link": "https://www.youtube.com/watch?v=bA22QfIhn9Y&t=312"
  },
  {
    "link": "https://www.youtube.com/watch?v=bA22QfIhn9Y&t=313"
  },
  {
    "link": "https://www.youtube.com/watch?v=bA22QfIhn9Y&t=314"
  },
  {
    "link": "https://www.youtube.com/watch?v=bA22QfIhn9Y&t=411"
  },
  {
    "link": "https://www.youtube.com/watch?v=bA22QfIhn9Y&t=412"
  },
  {
    "link": "https://www.youtube.com/watch?v=bA22QfIhn9Y&t=413"
  },
  {
    "link": "https://www.youtube.com/watch?v=bA22QfIhn9Y&t=414"
  },
  {
    "link": "https://www.youtube.com/watch?v=bA22QfIhn9Y&t=415"
  },
  {
    "link": "https://www.youtube.com/watch?v=bA22QfIhn9Y&t=748"
  },
  {
    "link": "https://www.youtube.com/watch?v=bA22QfIhn9Y&t=750"
  },
  {
    "link": "https://www.youtube.com/watch?v=bA22QfIhn9Y&t=751"
  },
  {
    "link": "https://www.youtube.com/watch?v=bA22QfIhn9Y&t=752"
  }
]