[
  {
    "link": "https://www.youtube.com/watch?v=Mf9lCVDbmqA&t=283"
  },
  {
    "link": "https://www.youtube.com/watch?v=Mf9lCVDbmqA&t=284"
  },
  {
    "link": "https://www.youtube.com/watch?v=Mf9lCVDbmqA&t=285"
  },
  {
    "link": "https://www.youtube.com/watch?v=Mf9lCVDbmqA&t=286"
  },
  {
    "link": "https://www.youtube.com/watch?v=Mf9lCVDbmqA&t=287"
  },
  {
    "link": "https://www.youtube.com/watch?v=Mf9lCVDbmqA&t=288"
  },
  {
    "link": "https://www.youtube.com/watch?v=Mf9lCVDbmqA&t=289"
  },
  {
    "link": "https://www.youtube.com/watch?v=Mf9lCVDbmqA&t=290"
  },
  {
    "link": "https://www.youtube.com/watch?v=Mf9lCVDbmqA&t=291"
  },
  {
    "link": "https://www.youtube.com/watch?v=Mf9lCVDbmqA&t=292"
  },
  {
    "link": "https://www.youtube.com/watch?v=Mf9lCVDbmqA&t=293"
  },
  {
    "link": "https://www.youtube.com/watch?v=Mf9lCVDbmqA&t=294"
  }
]