[
  {
    "link": "https://www.youtube.com/watch?v=qwyg_PIhC0w&t=1266"
  },
  {
    "link": "https://www.youtube.com/watch?v=qwyg_PIhC0w&t=1267"
  },
  {
    "link": "https://www.youtube.com/watch?v=qwyg_PIhC0w&t=1268"
  },
  {
    "link": "https://www.youtube.com/watch?v=qwyg_PIhC0w&t=1269"
  },
  {
    "link": "https://www.youtube.com/watch?v=qwyg_PIhC0w&t=1270"
  },
  {
    "link": "https://www.youtube.com/watch?v=qwyg_PIhC0w&t=1271"
  },
  {
    "link": "https://www.youtube.com/watch?v=qwyg_PIhC0w&t=1273"
  },
  {
    "link": "https://www.youtube.com/watch?v=qwyg_PIhC0w&t=1274"
  },
  {
    "link": "https://www.youtube.com/watch?v=qwyg_PIhC0w&t=1275"
  },
  {
    "link": "https://www.youtube.com/watch?v=qwyg_PIhC0w&t=1276"
  },
  {
    "link": "https://www.youtube.com/watch?v=qwyg_PIhC0w&t=1277"
  },
  {
    "link": "https://www.youtube.com/watch?v=qwyg_PIhC0w&t=1278"
  },
  {
    "link": "https://www.youtube.com/watch?v=qwyg_PIhC0w&t=1280"
  },
  {
    "link": "https://www.youtube.com/watch?v=qwyg_PIhC0w&t=1281"
  },
  {
    "link": "https://www.youtube.com/watch?v=qwyg_PIhC0w&t=1283"
  },
  {
    "link": "https://www.youtube.com/watch?v=qwyg_PIhC0w&t=1284"
  },
  {
    "link": "https://www.youtube.com/watch?v=qwyg_PIhC0w&t=1285"
  },
  {
    "link": "https://www.youtube.com/watch?v=qwyg_PIhC0w&t=1286"
  },
  {
    "link": "https://www.youtube.com/watch?v=qwyg_PIhC0w&t=1296"
  },
  {
    "link": "https://www.youtube.com/watch?v=qwyg_PIhC0w&t=1297"
  },
  {
    "link": "https://www.youtube.com/watch?v=qwyg_PIhC0w&t=1298"
  },
  {
    "link": "https://www.youtube.com/watch?v=qwyg_PIhC0w&t=1299"
  },
  {
    "link": "https://www.youtube.com/watch?v=qwyg_PIhC0w&t=1300"
  },
  {
    "link": "https://www.youtube.com/watch?v=qwyg_PIhC0w&t=1301"
  },
  {
    "link": "https://www.youtube.com/watch?v=qwyg_PIhC0w&t=1302"
  },
  {
    "link": "https://www.youtube.com/watch?v=qwyg_PIhC0w&t=1303"
  },
  {
    "link": "https://www.youtube.com/watch?v=qwyg_PIhC0w&t=1304"
  },
  {
    "link": "https://www.youtube.com/watch?v=qwyg_PIhC0w&t=1305"
  },
  {
    "link": "https://www.youtube.com/watch?v=qwyg_PIhC0w&t=1306"
  },
  {
    "link": "https://www.youtube.com/watch?v=qwyg_PIhC0w&t=1307"
  },
  {
    "link": "https://www.youtube.com/watch?v=qwyg_PIhC0w&t=1308"
  },
  {
    "link": "https://www.youtube.com/watch?v=qwyg_PIhC0w&t=1309"
  },
  {
    "link": "https://www.youtube.com/watch?v=qwyg_PIhC0w&t=1310"
  },
  {
    "link": "https://www.youtube.com/watch?v=qwyg_PIhC0w&t=1311"
  },
  {
    "link": "https://www.youtube.com/watch?v=qwyg_PIhC0w&t=1312"
  },
  {
    "link": "https://www.youtube.com/watch?v=qwyg_PIhC0w&t=1313"
  },
  {
    "link": "https://www.youtube.com/watch?v=qwyg_PIhC0w&t=1314"
  },
  {
    "link": "https://www.youtube.com/watch?v=qwyg_PIhC0w&t=1315"
  },
  {
    "link": "https://www.youtube.com/watch?v=qwyg_PIhC0w&t=1316"
  },
  {
    "link": "https://www.youtube.com/watch?v=qwyg_PIhC0w&t=1317"
  },
  {
    "link": "https://www.youtube.com/watch?v=qwyg_PIhC0w&t=1318"
  },
  {
    "link": "https://www.youtube.com/watch?v=qwyg_PIhC0w&t=1319"
  }
]