[
  {
    "link": "https://www.youtube.com/watch?v=xHwHk7CQDTs&t=434"
  },
  {
    "link": "https://www.youtube.com/watch?v=xHwHk7CQDTs&t=435"
  },
  {
    "link": "https://www.youtube.com/watch?v=xHwHk7CQDTs&t=436"
  },
  {
    "link": "https://www.youtube.com/watch?v=xHwHk7CQDTs&t=437"
  },
  {
    "link": "https://www.youtube.com/watch?v=xHwHk7CQDTs&t=438"
  },
  {
    "link": "https://www.youtube.com/watch?v=xHwHk7CQDTs&t=439"
  },
  {
    "link": "https://www.youtube.com/watch?v=xHwHk7CQDTs&t=440"
  },
  {
    "link": "https://www.youtube.com/watch?v=xHwHk7CQDTs&t=441"
  },
  {
    "link": "https://www.youtube.com/watch?v=xHwHk7CQDTs&t=442"
  },
  {
    "link": "https://www.youtube.com/watch?v=xHwHk7CQDTs&t=443"
  },
  {
    "link": "https://www.youtube.com/watch?v=xHwHk7CQDTs&t=444"
  },
  {
    "link": "https://www.youtube.com/watch?v=xHwHk7CQDTs&t=445"
  },
  {
    "link": "https://www.youtube.com/watch?v=xHwHk7CQDTs&t=446"
  },
  {
    "link": "https://www.youtube.com/watch?v=xHwHk7CQDTs&t=448"
  },
  {
    "link": "https://www.youtube.com/watch?v=xHwHk7CQDTs&t=449"
  },
  {
    "link": "https://www.youtube.com/watch?v=xHwHk7CQDTs&t=451"
  },
  {
    "link": "https://www.youtube.com/watch?v=xHwHk7CQDTs&t=452"
  },
  {
    "link": "https://www.youtube.com/watch?v=xHwHk7CQDTs&t=453"
  },
  {
    "link": "https://www.youtube.com/watch?v=xHwHk7CQDTs&t=454"
  },
  {
    "link": "https://www.youtube.com/watch?v=xHwHk7CQDTs&t=456"
  },
  {
    "link": "https://www.youtube.com/watch?v=xHwHk7CQDTs&t=457"
  },
  {
    "link": "https://www.youtube.com/watch?v=xHwHk7CQDTs&t=458"
  }
]