[
  {
    "link": "https://www.youtube.com/watch?v=c6vnlHXBPDw&t=962"
  },
  {
    "link": "https://www.youtube.com/watch?v=c6vnlHXBPDw&t=963"
  },
  {
    "link": "https://www.youtube.com/watch?v=c6vnlHXBPDw&t=964"
  },
  {
    "link": "https://www.youtube.com/watch?v=c6vnlHXBPDw&t=965"
  },
  {
    "link": "https://www.youtube.com/watch?v=c6vnlHXBPDw&t=966"
  },
  {
    "link": "https://www.youtube.com/watch?v=c6vnlHXBPDw&t=967"
  },
  {
    "link": "https://www.youtube.com/watch?v=c6vnlHXBPDw&t=968"
  },
  {
    "link": "https://www.youtube.com/watch?v=c6vnlHXBPDw&t=969"
  },
  {
    "link": "https://www.youtube.com/watch?v=c6vnlHXBPDw&t=970"
  },
  {
    "link": "https://www.youtube.com/watch?v=c6vnlHXBPDw&t=971"
  },
  {
    "link": "https://www.youtube.com/watch?v=c6vnlHXBPDw&t=972"
  },
  {
    "link": "https://www.youtube.com/watch?v=c6vnlHXBPDw&t=973"
  },
  {
    "link": "https://www.youtube.com/watch?v=c6vnlHXBPDw&t=974"
  },
  {
    "link": "https://www.youtube.com/watch?v=c6vnlHXBPDw&t=975"
  },
  {
    "link": "https://www.youtube.com/watch?v=c6vnlHXBPDw&t=976"
  }
]