[{"link":"https://www.youtube.com/watch?v=uLfrt7Atldo&t=381"},{"link":"https://www.youtube.com/watch?v=uLfrt7Atldo&t=382"},{"link":"https://www.youtube.com/watch?v=uLfrt7Atldo&t=383"},{"link":"https://www.youtube.com/watch?v=uLfrt7Atldo&t=384"},{"link":"https://www.youtube.com/watch?v=uLfrt7Atldo&t=385"},{"link":"https://www.youtube.com/watch?v=uLfrt7Atldo&t=386"},{"link":"https://www.youtube.com/watch?v=uLfrt7Atldo&t=387"},{"link":"https://www.youtube.com/watch?v=uLfrt7Atldo&t=388"},{"link":"https://www.youtube.com/watch?v=uLfrt7Atldo&t=389"},{"link":"https://www.youtube.com/watch?v=uLfrt7Atldo&t=390"},{"link":"https://www.youtube.com/watch?v=uLfrt7Atldo&t=391"},{"link":"https://www.youtube.com/watch?v=uLfrt7Atldo&t=392"},{"link":"https://www.youtube.com/watch?v=uLfrt7Atldo&t=393"},{"link":"https://www.youtube.com/watch?v=uLfrt7Atldo&t=394"},{"link":"https://www.youtube.com/watch?v=uLfrt7Atldo&t=395"},{"link":"https://www.youtube.com/watch?v=uLfrt7Atldo&t=396"},{"link":"https://www.youtube.com/watch?v=uLfrt7Atldo&t=397"},{"link":"https://www.youtube.com/watch?v=uLfrt7Atldo&t=398"},{"link":"https://www.youtube.com/watch?v=uLfrt7Atldo&t=399"},{"link":"https://www.youtube.com/watch?v=uLfrt7Atldo&t=403"},{"link":"https://www.youtube.com/watch?v=uLfrt7Atldo&t=404"}]