[{"link":"https://www.youtube.com/watch?v=stJdtMbtiOU&t=685"},{"link":"https://www.youtube.com/watch?v=stJdtMbtiOU&t=686"},{"link":"https://www.youtube.com/watch?v=stJdtMbtiOU&t=687"},{"link":"https://www.youtube.com/watch?v=stJdtMbtiOU&t=690"},{"link":"https://www.youtube.com/watch?v=stJdtMbtiOU&t=705"},{"link":"https://www.youtube.com/watch?v=stJdtMbtiOU&t=706"},{"link":"https://www.youtube.com/watch?v=stJdtMbtiOU&t=707"},{"link":"https://www.youtube.com/watch?v=stJdtMbtiOU&t=708"},{"link":"https://www.youtube.com/watch?v=stJdtMbtiOU&t=712"},{"link":"https://www.youtube.com/watch?v=stJdtMbtiOU&t=720"},{"link":"https://www.youtube.com/watch?v=stJdtMbtiOU&t=721"},{"link":"https://www.youtube.com/watch?v=stJdtMbtiOU&t=722"},{"link":"https://www.youtube.com/watch?v=stJdtMbtiOU&t=726"},{"link":"https://www.youtube.com/watch?v=stJdtMbtiOU&t=728"},{"link":"https://www.youtube.com/watch?v=stJdtMbtiOU&t=735"},{"link":"https://www.youtube.com/watch?v=stJdtMbtiOU&t=738"},{"link":"https://www.youtube.com/watch?v=stJdtMbtiOU&t=739"},{"link":"https://www.youtube.com/watch?v=stJdtMbtiOU&t=740"},{"link":"https://www.youtube.com/watch?v=stJdtMbtiOU&t=741"},{"link":"https://www.youtube.com/watch?v=stJdtMbtiOU&t=742"},{"link":"https://www.youtube.com/watch?v=stJdtMbtiOU&t=743"},{"link":"https://www.youtube.com/watch?v=stJdtMbtiOU&t=744"},{"link":"https://www.youtube.com/watch?v=stJdtMbtiOU&t=745"},{"link":"https://www.youtube.com/watch?v=stJdtMbtiOU&t=746"},{"link":"https://www.youtube.com/watch?v=stJdtMbtiOU&t=747"},{"link":"https://www.youtube.com/watch?v=stJdtMbtiOU&t=748"}]