[{"link":"https://www.youtube.com/watch?v=stJdtMbtiOU&t=143"},{"link":"https://www.youtube.com/watch?v=stJdtMbtiOU&t=144"},{"link":"https://www.youtube.com/watch?v=stJdtMbtiOU&t=145"},{"link":"https://www.youtube.com/watch?v=stJdtMbtiOU&t=146"},{"link":"https://www.youtube.com/watch?v=stJdtMbtiOU&t=147"},{"link":"https://www.youtube.com/watch?v=stJdtMbtiOU&t=148"},{"link":"https://www.youtube.com/watch?v=stJdtMbtiOU&t=149"},{"link":"https://www.youtube.com/watch?v=stJdtMbtiOU&t=150"},{"link":"https://www.youtube.com/watch?v=stJdtMbtiOU&t=151"},{"link":"https://www.youtube.com/watch?v=stJdtMbtiOU&t=152"},{"link":"https://www.youtube.com/watch?v=stJdtMbtiOU&t=153"},{"link":"https://www.youtube.com/watch?v=stJdtMbtiOU&t=154"},{"link":"https://www.youtube.com/watch?v=stJdtMbtiOU&t=156"},{"link":"https://www.youtube.com/watch?v=stJdtMbtiOU&t=157"},{"link":"https://www.youtube.com/watch?v=stJdtMbtiOU&t=158"},{"link":"https://www.youtube.com/watch?v=stJdtMbtiOU&t=161"}]