[
  {
    "link": "https://www.youtube.com/watch?v=fjJha8p-CXY&t=118"
  },
  {
    "link": "https://www.youtube.com/watch?v=oMQwnMR6OVk&t=48"
  },
  {
    "link": "https://www.youtube.com/watch?v=oMQwnMR6OVk&t=547"
  },
  {
    "link": "https://www.youtube.com/watch?v=qzydxPgPKzs&t=190"
  },
  {
    "link": "https://www.youtube.com/watch?v=qzydxPgPKzs&t=192"
  },
  {
    "link": "https://www.youtube.com/watch?v=qzydxPgPKzs&t=193"
  },
  {
    "link": "https://www.youtube.com/watch?v=qzydxPgPKzs&t=194"
  },
  {
    "link": "https://www.youtube.com/watch?v=qzydxPgPKzs&t=195"
  },
  {
    "link": "https://www.youtube.com/watch?v=qzydxPgPKzs&t=196"
  },
  {
    "link": "https://www.youtube.com/watch?v=qzydxPgPKzs&t=197"
  },
  {
    "link": "https://www.youtube.com/watch?v=qzydxPgPKzs&t=198"
  },
  {
    "link": "https://www.youtube.com/watch?v=qzydxPgPKzs&t=199"
  },
  {
    "link": "https://www.youtube.com/watch?v=qzydxPgPKzs&t=200"
  },
  {
    "link": "https://www.youtube.com/watch?v=qzydxPgPKzs&t=201"
  },
  {
    "link": "https://www.youtube.com/watch?v=qzydxPgPKzs&t=202"
  },
  {
    "link": "https://www.youtube.com/watch?v=qzydxPgPKzs&t=203"
  },
  {
    "link": "https://www.youtube.com/watch?v=qzydxPgPKzs&t=204"
  },
  {
    "link": "https://www.youtube.com/watch?v=qzydxPgPKzs&t=205"
  },
  {
    "link": "https://www.youtube.com/watch?v=qzydxPgPKzs&t=206"
  },
  {
    "link": "https://www.youtube.com/watch?v=qzydxPgPKzs&t=207"
  },
  {
    "link": "https://www.youtube.com/watch?v=qzydxPgPKzs&t=209"
  },
  {
    "link": "https://www.youtube.com/watch?v=qzydxPgPKzs&t=215"
  },
  {
    "link": "https://www.youtube.com/watch?v=qzydxPgPKzs&t=216"
  },
  {
    "link": "https://www.youtube.com/watch?v=qzydxPgPKzs&t=217"
  },
  {
    "link": "https://www.youtube.com/watch?v=qzydxPgPKzs&t=218"
  },
  {
    "link": "https://www.youtube.com/watch?v=W5c3cDDN6yI&t=339"
  },
  {
    "link": "https://www.youtube.com/watch?v=W5c3cDDN6yI&t=560"
  }
]