[{"link":"https://www.youtube.com/watch?v=eZpcCvzaKBw&t=272"},{"link":"https://www.youtube.com/watch?v=eZpcCvzaKBw&t=273"},{"link":"https://www.youtube.com/watch?v=eZpcCvzaKBw&t=274"},{"link":"https://www.youtube.com/watch?v=eZpcCvzaKBw&t=275"},{"link":"https://www.youtube.com/watch?v=eZpcCvzaKBw&t=276"},{"link":"https://www.youtube.com/watch?v=eZpcCvzaKBw&t=278"},{"link":"https://www.youtube.com/watch?v=eZpcCvzaKBw&t=279"},{"link":"https://www.youtube.com/watch?v=eZpcCvzaKBw&t=280"},{"link":"https://www.youtube.com/watch?v=eZpcCvzaKBw&t=281"},{"link":"https://www.youtube.com/watch?v=eZpcCvzaKBw&t=299"}]