[{"link":"https://www.youtube.com/watch?v=qP7JsrhVg6w&t=1116"},{"link":"https://www.youtube.com/watch?v=qP7JsrhVg6w&t=414"},{"link":"https://www.youtube.com/watch?v=qP7JsrhVg6w&t=416"},{"link":"https://www.youtube.com/watch?v=qP7JsrhVg6w&t=417"},{"link":"https://www.youtube.com/watch?v=qP7JsrhVg6w&t=419"},{"link":"https://www.youtube.com/watch?v=qP7JsrhVg6w&t=421"},{"link":"https://www.youtube.com/watch?v=qP7JsrhVg6w&t=641"},{"link":"https://www.youtube.com/watch?v=qP7JsrhVg6w&t=642"},{"link":"https://www.youtube.com/watch?v=qP7JsrhVg6w&t=643"},{"link":"https://www.youtube.com/watch?v=qP7JsrhVg6w&t=644"},{"link":"https://www.youtube.com/watch?v=qP7JsrhVg6w&t=645"},{"link":"https://www.youtube.com/watch?v=qP7JsrhVg6w&t=646"},{"link":"https://www.youtube.com/watch?v=qP7JsrhVg6w&t=647"},{"link":"https://www.youtube.com/watch?v=qP7JsrhVg6w&t=648"},{"link":"https://www.youtube.com/watch?v=qP7JsrhVg6w&t=649"},{"link":"https://www.youtube.com/watch?v=qP7JsrhVg6w&t=657"},{"link":"https://www.youtube.com/watch?v=qP7JsrhVg6w&t=658"}]